photonic_logic-2.4.4.dist-info/licenses/LICENSE
plogic/__init__.py
plogic/__main__.py
plogic/cli.py
plogic/controller.py
plogic/analysis/__init__.py
plogic/analysis/power.py
plogic/config/__init__.py
plogic/config/constants.py
plogic/integration/__init__.py
plogic/integration/optics.py
plogic/materials/__init__.py
plogic/materials/database.json
plogic/materials/hybrid.py
plogic/materials/platforms.py
plogic/opt_utils/array_safety.py
plogic/optimization/__init__.py
plogic/optimization/accelerator_system.py
plogic/optimization/accelerator_system_fixed.py
plogic/optimization/acquisition.py
plogic/optimization/bounds.py
plogic/optimization/manufacturing_constraints.py
plogic/optimization/optimizer_fixes.py
plogic/optimization/optimizer_fixes_v2.py
plogic/optimization/photonic_objectives.py
plogic/optimization/physics_validation.py
plogic/optimization/plateau_breaker.py
plogic/optimization/simple_optimizer.py
plogic/optimization/surrogates.py
plogic/optimization/thermal_cosimulation.py
plogic/physics/__init__.py
plogic/physics/metrics.py
plogic/utils/__init__.py
plogic/utils/console_encoding.py
plogic/utils/formatting.py
plogic/utils/io.py
plogic/utils/optimize_utils.py
plogic/utils/plateau_utils.py
plogic/utils/reproducibility.py
plogic/utils/statistics.py
plogic/utils/switching.py
photonic_logic-2.4.4.dist-info/METADATA
photonic_logic-2.4.4.dist-info/WHEEL
photonic_logic-2.4.4.dist-info/entry_points.txt
photonic_logic-2.4.4.dist-info/top_level.txt
photonic_logic-2.4.4.dist-info/RECORD
