Metadata-Version: 2.4
Name: photonic-logic
Version: 2.4.4
Summary: Programmable Photonic Logic: control, simulation, and characterization
Author: Open Photonics Lab
License: MIT License
Project-URL: Homepage, https://github.com/grapheneaffiliate/photonic-logic
Project-URL: Issues, https://github.com/grapheneaffiliate/photonic-logic/issues
Project-URL: Documentation, https://github.com/grapheneaffiliate/photonic-logic#readme
Requires-Python: >=3.10
License-File: LICENSE
Requires-Dist: numpy
Requires-Dist: pandas
Requires-Dist: scipy
Requires-Dist: matplotlib
Requires-Dist: typer
Requires-Dist: rich
Provides-Extra: dev
Requires-Dist: pytest>=8; extra == "dev"
Requires-Dist: pytest-cov>=5; extra == "dev"
Requires-Dist: ruff>=0.5; extra == "dev"
Requires-Dist: black>=24.3.0; extra == "dev"
Requires-Dist: mypy>=1.10.0; extra == "dev"
Requires-Dist: pre-commit>=3.7.0; extra == "dev"
Requires-Dist: hypothesis>=6; extra == "dev"
Dynamic: license-file
